image_processing_lfrossinhole/__init__.py
image_processing_lfrossinhole/processing/__init__.py
image_processing_lfrossinhole/processing/combination.py
image_processing_lfrossinhole/processing/transformation.py
image_processing_lfrossinhole/utils/__init__.py
image_processing_lfrossinhole/utils/io.py
image_processing_lfrossinhole/utils/plot.py
image_processing_lfrossinhole-0.0.2.dist-info/METADATA
image_processing_lfrossinhole-0.0.2.dist-info/WHEEL
image_processing_lfrossinhole-0.0.2.dist-info/top_level.txt
image_processing_lfrossinhole-0.0.2.dist-info/RECORD
