Metadata-Version: 2.1
Name: image_processing_lfrossinhole
Version: 0.0.2
Summary: Image Processing Package using Skimage
Home-page: https://github.com/lfrossinhole/image-processing-package
Author: Lucas Feitosa
Requires-Python: >=3.5
Requires-Dist: matplotlib
Requires-Dist: numpy
Requires-Dist: scikit-image >=0.16.1
